embeddings_visualizer/app.py
embeddings_visualizer/embeddings.ipynb
embeddings_visualizer/main.py
embeddings_visualizer/questions.csv
embeddings_visualizer-0.0.9.dist-info/METADATA
embeddings_visualizer-0.0.9.dist-info/WHEEL
embeddings_visualizer-0.0.9.dist-info/entry_points.txt
embeddings_visualizer-0.0.9.dist-info/RECORD
