Metadata-Version: 2.1
Name: embeddings-visualizer
Version: 0.0.9
Summary: 
Author: markus
Author-email: datamastery87@gmail.com
Requires-Python: >=3.9, !=2.7.*, !=3.0.*, !=3.1.*, !=3.2.*, !=3.3.*, !=3.4.*, !=3.5.*, !=3.6.*, !=3.7.*, !=3.8.*
Classifier: Programming Language :: Python :: 3
Classifier: Programming Language :: Python :: 3.9
Classifier: Programming Language :: Python :: 3.10
Classifier: Programming Language :: Python :: 3.11
Requires-Dist: langchain (>=0.0.200)
Requires-Dist: matplotlib (>=3.6.0)
Requires-Dist: numpy (>=1.20.0)
Requires-Dist: openai (>=0.27.0)
Requires-Dist: pandas (>=2.0.0)
Requires-Dist: plotly (>=5.0.0)
Requires-Dist: python-dotenv (>=1.0.0,<2.0.0)
Requires-Dist: scikit-learn (>=1.2.0,<2.0.0)
Requires-Dist: streamlit (>=1.20.0)
Requires-Dist: typer (>=0.7.0)
